sededu/__init__.py
sededu/_readme.json
sededu/_version.py
sededu/about.py
sededu/base.py
sededu/category.py
sededu/exceptions.py
sededu/navigation.py
sededu/root.py
sededu/sededu.py
sededu/utilities.py
sededu/modules/coasts/empty.txt
sededu/modules/deserts/empty.txt
sededu/modules/landscapes/empty.txt
sededu/modules/landscapes/hillslope_creep/LICENSE
sededu/modules/landscapes/hillslope_creep/README.md
sededu/modules/landscapes/hillslope_creep/about.json
sededu/modules/landscapes/hillslope_creep/run_hillslope_creep.py
sededu/modules/landscapes/hillslope_creep/setup.py
sededu/modules/landscapes/hillslope_creep/docs/introduction.md
sededu/modules/landscapes/hillslope_creep/docs/introduction.pdf
sededu/modules/landscapes/hillslope_creep/docs/refs.bib
sededu/modules/landscapes/hillslope_creep/hillslope_creep/__init__.py
sededu/modules/landscapes/hillslope_creep/hillslope_creep/_version.py
sededu/modules/landscapes/hillslope_creep/hillslope_creep/hillslope_creep.py
sededu/modules/landscapes/hillslope_creep/hillslope_creep/widgets.py
sededu/modules/landscapes/hillslope_creep/private/hillslope_creep.jpeg
sededu/modules/landscapes/hillslope_creep/private/hillslope_creep_demo.png
sededu/modules/landscapes/hillslope_creep/private/hillslope_drawing.png
sededu/modules/landscapes/hillslope_creep/private/hillslope_model_demo.gif
sededu/modules/landscapes/rain_table/.appveyor.yml
sededu/modules/landscapes/rain_table/.travis.yml
sededu/modules/landscapes/rain_table/LICENSE
sededu/modules/landscapes/rain_table/README.md
sededu/modules/landscapes/rain_table/about.json
sededu/modules/landscapes/rain_table/run_rain_table.py
sededu/modules/landscapes/rain_table/setup.py
sededu/modules/landscapes/rain_table/.ci/appveyor/anaconda_build_upload.py
sededu/modules/landscapes/rain_table/.ci/conda-recipe/bld.bat
sededu/modules/landscapes/rain_table/.ci/conda-recipe/build.sh
sededu/modules/landscapes/rain_table/.ci/conda-recipe/meta.yaml
sededu-1.1.10.dist-info/LICENSE.txt
sededu-1.1.10.dist-info/METADATA
sededu-1.1.10.dist-info/WHEEL
sededu-1.1.10.dist-info/top_level.txt
sededu-1.1.10.dist-info/RECORD
