Metadata-Version: 2.1
Name: sededu
Version: 1.1.10
Summary: sediment-related educational activity suite
Home-page: https://github.com/sededu/sededu
Author: Andrew J. Moodie and other contributors
Author-email: amoodie@utexas.edu
License: LICENSE.txt
Project-URL: Bug Reports, https://github.com/sededu/sededu/issues
Project-URL: Source, https://github.com/sededu/sededu/
Platform: UNKNOWN
Classifier: Development Status :: 4 - Beta
Classifier: License :: OSI Approved :: GNU General Public License v3 (GPLv3)
Classifier: Intended Audience :: Education
Classifier: Intended Audience :: End Users/Desktop
Classifier: Intended Audience :: Science/Research
Classifier: Topic :: Education
Requires-Python: >=3
License-File: LICENSE.txt
Requires-Dist: scipy
Requires-Dist: numpy
Requires-Dist: matplotlib
Requires-Dist: shapely
Requires-Dist: pillow
Requires-Dist: pyqt5
